crmchatbot/__init__.py
crmchatbot/access_token.py
crmchatbot/agent.py
crmchatbot/answerRequests.py
crmchatbot/formatData.py
crmchatbot/get_data.py
crmchatbot/handle_user_input.py
crmchatbot/response.py
crmchatbot/syntax.py
crmchatbot-0.1.3.dist-info/LICENSE
crmchatbot-0.1.3.dist-info/METADATA
crmchatbot-0.1.3.dist-info/WHEEL
crmchatbot-0.1.3.dist-info/top_level.txt
crmchatbot-0.1.3.dist-info/RECORD
